hypergen_translation/__init__.py
hypergen_translation/admin.py
hypergen_translation/api.py
hypergen_translation/filters.py
hypergen_translation/models.py
hypergen_translation/plugins.py
hypergen_translation/management/__init__.py
hypergen_translation/management/commands/__init__.py
hypergen_translation/management/commands/hypergen_translation_collect.py
hypergen_translation/migrations/0001_initial.py
hypergen_translation/migrations/__init__.py
hypergen_translation_plugin-0.1.3.dist-info/LICENSE
hypergen_translation_plugin-0.1.3.dist-info/METADATA
hypergen_translation_plugin-0.1.3.dist-info/WHEEL
hypergen_translation_plugin-0.1.3.dist-info/top_level.txt
hypergen_translation_plugin-0.1.3.dist-info/RECORD
