Metadata-Version: 2.1
Name: hypergen-translation-plugin
Version: 0.1.3
Summary: Translation plugin for Django Hypergen
Home-page: https://github.com/runekaagaard/hypergen-translation-plugin/
Author: Rune Kaagaard
Author-email: rumi.kg@gmail.com
Project-URL: Bug Tracker, https://github.com/runekaagaard/hypergen-translation-plugin/issues
Classifier: Programming Language :: Python :: 3
Classifier: License :: OSI Approved :: Mozilla Public License 2.0 (MPL 2.0)
Classifier: Operating System :: OS Independent
Classifier: Framework :: Django
Classifier: Development Status :: 5 - Production/Stable
Requires-Python: >=3.7
License-File: LICENSE
